GameOfLife/__init__.py
GameOfLife/cell.py
GameOfLife/patterns.py
GameOfLife/world.py
GameOfLife/tests/__init__.py
GameOfLife/tests/test_cell.py
GameOfLife/tests/test_patterns.py
GameOfLife/tests/test_world.py
GameOfLife-0.1.2.data/scripts/CGameOfLife.py
GameOfLife-0.1.2.data/scripts/PGameOfLife.py
GameOfLife-0.1.2.dist-info/DESCRIPTION.rst
GameOfLife-0.1.2.dist-info/METADATA
GameOfLife-0.1.2.dist-info/metadata.json
GameOfLife-0.1.2.dist-info/RECORD
GameOfLife-0.1.2.dist-info/top_level.txt
GameOfLife-0.1.2.dist-info/WHEEL
